filerepack/__init__.py
filerepack/__main__.py
filerepack/consts.py
filerepack/repack.py
filerepack/utils.py
filerepack-0.1.4.dist-info/AUTHORS.rst
filerepack-0.1.4.dist-info/LICENSE
filerepack-0.1.4.dist-info/METADATA
filerepack-0.1.4.dist-info/WHEEL
filerepack-0.1.4.dist-info/entry_points.txt
filerepack-0.1.4.dist-info/top_level.txt
filerepack-0.1.4.dist-info/RECORD
