Metadata-Version: 2.1
Name: filerepack
Version: 0.1.4
Summary: Repacks existing (un)compressed files for higher compression
Home-page: https://github.com/ivbeg/filesrepack
Author: Ivan Begtin
Author-email: ivan@begtin.tech
License: BSD
Keywords: files converter compression
Platform: UNKNOWN
Classifier: Development Status :: 2 - Pre-Alpha
Classifier: Intended Audience :: Developers
Classifier: License :: OSI Approved :: BSD License
Classifier: Natural Language :: English
Classifier: Programming Language :: Python :: 3
Classifier: Programming Language :: Python :: 3.3
Classifier: Programming Language :: Python :: 3.4
Classifier: Programming Language :: Python :: 3.5
Classifier: Programming Language :: Python :: 3.6
Classifier: Programming Language :: Python :: Implementation :: CPython
Classifier: Programming Language :: Python :: Implementation :: PyPy
License-File: LICENSE
License-File: AUTHORS.rst
Requires-Dist: typer (>=0.9.0)
Provides-Extra: parquet
Requires-Dist: duckdb (>=0.9.0) ; extra == 'parquet'
